memories/__init__.py
memories/cli.py
memories/config.py
memories/analyzers/__init__.py
memories/analyzers/change_detector.py
memories/config/__init__.py
memories/config/config.yaml
memories/core/__init__.py
memories/core/cold.py
memories/core/config.py
memories/core/database.py
memories/core/earth.py
memories/core/glacier.py
memories/core/hot.py
memories/core/memory_catalog.py
memories/core/memory_index.py
memories/core/memory_manager.py
memories/core/memory_query.py
memories/core/memory_retrieval.py
memories/core/memory_store.py
memories/core/memory_tiering.py
memories/core/red_hot.py
memories/core/unstructured.py
memories/core/warm.py
memories/core/glacier/__init__.py
memories/core/glacier/api_connector.py
memories/core/glacier/base.py
memories/core/glacier/factory.py
memories/core/glacier/memory.py
memories/core/glacier/artifacts/__init__.py
memories/core/glacier/artifacts/base.py
memories/core/glacier/artifacts/landsat.py
memories/core/glacier/artifacts/osm.py
memories/core/glacier/artifacts/overture.py
memories/core/glacier/artifacts/planetary.py
memories/core/glacier/artifacts/sentinel.py
memories/core/glacier/artifacts/base/__init__.py
memories/core/glacier/connectors/__init__.py
memories/core/glacier/connectors/gcs_connector.py
memories/core/memory/__init__.py
memories/data_acquisition/__init__.py
memories/data_acquisition/data_connectors.py
memories/data_acquisition/data_manager.py
memories/data_acquisition/data_sources.py
memories/data_acquisition/parquet_connector.py
memories/data_acquisition/connectors/parquet_connector.py
memories/data_acquisition/sources/__init__.py
memories/data_acquisition/sources/base.py
memories/data_acquisition/sources/cog_stac_api.py
memories/data_acquisition/sources/data_sources.py
memories/data_acquisition/sources/earth_engine_api.py
memories/data_acquisition/sources/mobile_metaverse.py
memories/data_acquisition/sources/unified_api.py
memories/data_acquisition/sources/wfs_api.py
memories/interface/__init__.py
memories_dev-2.0.8.dist-info/licenses/LICENSE
memories_dev-2.0.8.dist-info/METADATA
memories_dev-2.0.8.dist-info/WHEEL
memories_dev-2.0.8.dist-info/top_level.txt
memories_dev-2.0.8.dist-info/RECORD
