Metadata-Version: 2.4
Name: memories-dev
Version: 2.0.8
Summary: Collective Memory Infrastructure for AGI
Home-page: https://github.com/Vortx-AI/memories-dev
Author: Memories-dev
Author-email: Memories-dev Team <team@memories-app.com>
Maintainer-email: Memories-dev <hello@memories.dev>
License:                                  Apache License
Project-URL: Homepage, https://memories.dev
Project-URL: Documentation, https://docs.memories.dev
Project-URL: Repository, https://github.com/Vortx-AI/memories-dev.git
Project-URL: Issues, https://github.com/Vortx-AI/memories-dev/issues
Project-URL: Changelog, https://github.com/Vortx-AI/memories-dev/blob/main/CHANGELOG.md
Keywords: earth observation,data processing,memory management
Classifier: Development Status :: 5 - Production/Stable
Classifier: Programming Language :: Python :: 3.9
Classifier: Programming Language :: Python :: 3.10
Classifier: Programming Language :: Python :: 3.11
Classifier: Programming Language :: Python :: 3.12
Classifier: Programming Language :: Python :: 3.13
Classifier: Operating System :: OS Independent
Classifier: License :: OSI Approved :: Apache Software License
Classifier: Topic :: Scientific/Engineering :: GIS
Classifier: Topic :: Scientific/Engineering :: Artificial Intelligence
Classifier: Natural Language :: English
Requires-Python: >=3.9
License-File: LICENSE
Requires-Dist: torch>=2.2.0
Requires-Dist: transformers>=4.30.0
Requires-Dist: diffusers>=0.25.0
Requires-Dist: langchain>=0.1.0
Requires-Dist: langchain-community>=0.0.1
Requires-Dist: numpy<2.0.0,>=1.24.4
Requires-Dist: pandas>=2.0.0
Requires-Dist: duckdb>=0.9.0
Requires-Dist: pyarrow>=14.0.1
Requires-Dist: matplotlib>=3.7.0
Requires-Dist: geopandas>=0.14.0
Requires-Dist: rasterio>=1.3.8
Requires-Dist: shapely<3.0.0,>=2.0.0
Requires-Dist: mercantile>=1.2.1
Requires-Dist: mapbox-vector-tile>=2.0.1
Requires-Dist: pyproj>=3.6.1
Requires-Dist: pystac>=1.8.0
Requires-Dist: osmnx>=1.9.0
Requires-Dist: py6s>=1.9.0
Requires-Dist: geopy>=2.4.1
Requires-Dist: folium>=0.15.1
Requires-Dist: rtree>=1.1.0
Requires-Dist: owslib>=0.31.0
Requires-Dist: pillow>=10.0.0
Requires-Dist: opencv-python>=4.8.0
Requires-Dist: albumentations>=1.3.1
Requires-Dist: nltk>=3.8.1
Requires-Dist: faiss-cpu>=1.7.4
Requires-Dist: sentence-transformers>=2.2.0
Requires-Dist: duckdb>=0.9.0
Requires-Dist: xarray>=2023.0.0
Requires-Dist: dask>=2024.1.0
Requires-Dist: fastapi>=0.109.0
Requires-Dist: pydantic>=2.6.0
Requires-Dist: uvicorn>=0.27.0
Requires-Dist: aiohttp>=3.9.0
Requires-Dist: requests>=2.31.0
Requires-Dist: planetary-computer>=1.0.0
Requires-Dist: pystac-client>=0.8.3
Requires-Dist: earthengine-api>=0.1.390
Requires-Dist: tqdm>=4.65.0
Requires-Dist: python-dotenv>=1.0.0
Requires-Dist: pyyaml>=6.0.1
Requires-Dist: cryptography>=42.0.0
Requires-Dist: typing-extensions>=4.9.0
Requires-Dist: fsspec>=2024.2.0
Requires-Dist: noise>=1.2.2
Provides-Extra: py39
Requires-Dist: numpy<2.0.0,>=1.24.4; extra == "py39"
Requires-Dist: pandas<2.1.0,>=2.0.0; extra == "py39"
Requires-Dist: matplotlib<3.8.0; extra == "py39"
Requires-Dist: scikit-learn<1.4.0; extra == "py39"
Requires-Dist: albumentations<1.4.0; extra == "py39"
Requires-Dist: accelerate<1.4.0; extra == "py39"
Requires-Dist: shapely<2.0.0,>=1.7.0; extra == "py39"
Requires-Dist: mapbox-vector-tile<2.0.0,>=1.2.0; extra == "py39"
Provides-Extra: py310
Requires-Dist: numpy<2.0.0,>=1.24.4; extra == "py310"
Requires-Dist: pandas>=2.0.0; extra == "py310"
Requires-Dist: matplotlib>=3.7.0; extra == "py310"
Requires-Dist: scikit-learn>=1.3.0; extra == "py310"
Requires-Dist: shapely<2.0.0,>=1.7.0; extra == "py310"
Requires-Dist: mapbox-vector-tile<2.0.0,>=1.2.0; extra == "py310"
Provides-Extra: py311
Requires-Dist: numpy<2.0.0,>=1.24.4; extra == "py311"
Requires-Dist: pandas>=2.0.0; extra == "py311"
Requires-Dist: matplotlib>=3.7.0; extra == "py311"
Requires-Dist: scikit-learn>=1.3.0; extra == "py311"
Requires-Dist: shapely<2.0.0,>=1.7.0; extra == "py311"
Requires-Dist: mapbox-vector-tile<2.0.0,>=1.2.0; extra == "py311"
Provides-Extra: py312
Requires-Dist: numpy<2.0.0,>=1.26.0; extra == "py312"
Requires-Dist: pandas>=2.2.0; extra == "py312"
Requires-Dist: matplotlib>=3.8.0; extra == "py312"
Requires-Dist: scikit-learn>=1.3.0; extra == "py312"
Requires-Dist: shapely<2.0.0,>=1.7.0; extra == "py312"
Requires-Dist: mapbox-vector-tile<2.0.0,>=1.2.0; extra == "py312"
Provides-Extra: py313
Requires-Dist: numpy<2.0.0,>=1.26.0; extra == "py313"
Requires-Dist: pandas>=2.2.0; extra == "py313"
Requires-Dist: matplotlib>=3.8.0; extra == "py313"
Requires-Dist: scikit-learn>=1.3.0; extra == "py313"
Requires-Dist: shapely<3.0.0,>=2.0.0; extra == "py313"
Requires-Dist: mapbox-vector-tile>=2.0.1; extra == "py313"
Provides-Extra: gpu
Requires-Dist: torch>=2.2.0; extra == "gpu"
Requires-Dist: torchvision>=0.17.0; extra == "gpu"
Requires-Dist: torchaudio>=2.2.0; extra == "gpu"
Requires-Dist: faiss-gpu==1.7.2; extra == "gpu"
Requires-Dist: cupy-cuda12x>=12.0.0; extra == "gpu"
Requires-Dist: torch-scatter>=2.1.2; extra == "gpu"
Requires-Dist: torch-sparse>=0.6.18; extra == "gpu"
Requires-Dist: torch-cluster>=1.6.3; extra == "gpu"
Requires-Dist: torch-geometric>=2.4.0; extra == "gpu"
Provides-Extra: dev
Requires-Dist: pytest>=8.3.4; extra == "dev"
Requires-Dist: pytest-asyncio>=0.23.5; extra == "dev"
Requires-Dist: pytest-cov>=6.0.0; extra == "dev"
Requires-Dist: pytest-mock>=3.14.0; extra == "dev"
Requires-Dist: pytest-xdist>=3.6.1; extra == "dev"
Requires-Dist: pytest-benchmark>=4.0.0; extra == "dev"
Requires-Dist: pytest-timeout>=2.2.0; extra == "dev"
Requires-Dist: black>=24.1.0; extra == "dev"
Requires-Dist: flake8>=7.0.0; extra == "dev"
Requires-Dist: mypy>=1.8.0; extra == "dev"
Requires-Dist: isort>=5.13.0; extra == "dev"
Requires-Dist: pre-commit>=3.6.0; extra == "dev"
Provides-Extra: docs
Requires-Dist: sphinx>=7.2.6; extra == "docs"
Requires-Dist: sphinx-rtd-theme>=2.0.0; extra == "docs"
Requires-Dist: sphinx-autodoc-typehints>=2.0.1; (python_version >= "3.12" and python_version < "3.13") and extra == "docs"
Requires-Dist: nbsphinx>=0.9.3; extra == "docs"
Requires-Dist: pandoc>=2.3; extra == "docs"
Requires-Dist: typing-extensions>=4.9.0; extra == "docs"
Requires-Dist: docutils>=0.20.1; extra == "docs"
Requires-Dist: packaging>=23.2; extra == "docs"
Requires-Dist: furo>=2024.1.29; extra == "docs"
Requires-Dist: sphinx-copybutton>=0.5.2; extra == "docs"
Requires-Dist: myst-parser>=2.0.0; extra == "docs"
Requires-Dist: platformdirs>=4.2.0; extra == "docs"
Requires-Dist: sphinx-design>=0.5.0; extra == "docs"
Requires-Dist: sphinxcontrib-mermaid>=0.9.2; extra == "docs"
Requires-Dist: sphinx-tabs>=3.4.1; extra == "docs"
Requires-Dist: sphinx-togglebutton>=0.3.2; extra == "docs"
Requires-Dist: sphinx-favicon>=1.0.1; extra == "docs"
Requires-Dist: sphinx-sitemap>=2.5.1; extra == "docs"
Requires-Dist: sphinx-last-updated-by-git>=0.3.6; extra == "docs"
Provides-Extra: test
Requires-Dist: pytest>=8.3.4; extra == "test"
Requires-Dist: pytest-asyncio>=0.23.5; extra == "test"
Requires-Dist: pytest-cov>=6.0.0; extra == "test"
Requires-Dist: pytest-mock>=3.14.0; extra == "test"
Requires-Dist: pytest-xdist>=3.6.1; extra == "test"
Requires-Dist: pytest-benchmark>=4.0.0; extra == "test"
Dynamic: author
Dynamic: home-page
Dynamic: license-file
Dynamic: requires-python
